pyrfx/__init__.py
pyrfx/approve_token.py
pyrfx/config_manager.py
pyrfx/contracts/balance_abi.json
pyrfx/contracts/token_approval.json
pyrfx/contracts/weth.json
pyrfx/contracts/zksync/data_store.json
pyrfx/contracts/zksync/deposit_vault.json
pyrfx/contracts/zksync/errors.json
pyrfx/contracts/zksync/event_emitter.json
pyrfx/contracts/zksync/exchange_router.json
pyrfx/contracts/zksync/order_handler.json
pyrfx/contracts/zksync/order_vault.json
pyrfx/contracts/zksync/reader.json
pyrfx/contracts/zksync/referral_storage.json
pyrfx/contracts/zksync/router.json
pyrfx/contracts/zksync/withdrawal_vault.json
pyrfx/contracts/zksync_internal/data_store.json
pyrfx/contracts/zksync_internal/deposit_vault.json
pyrfx/contracts/zksync_internal/errors.json
pyrfx/contracts/zksync_internal/event_emitter.json
pyrfx/contracts/zksync_internal/exchange_router.json
pyrfx/contracts/zksync_internal/order_handler.json
pyrfx/contracts/zksync_internal/order_vault.json
pyrfx/contracts/zksync_internal/reader.json
pyrfx/contracts/zksync_internal/referral_storage.json
pyrfx/contracts/zksync_internal/router.json
pyrfx/contracts/zksync_internal/withdrawal_vault.json
pyrfx/custom_error_parser.py
pyrfx/gas_utils.py
pyrfx/get/__init__.py
pyrfx/get/available_liquidity.py
pyrfx/get/borrow_apr.py
pyrfx/get/claimable_fees.py
pyrfx/get/contract_balance.py
pyrfx/get/data.py
pyrfx/get/estimate_swap_output.py
pyrfx/get/funding_apr.py
pyrfx/get/markets.py
pyrfx/get/open_interest.py
pyrfx/get/open_positions.py
pyrfx/get/oracle_prices.py
pyrfx/get/pool_tvl.py
pyrfx/get/rp_prices.py
pyrfx/keys.py
pyrfx/order/__init__.py
pyrfx/order/arg_parser_liquidity.py
pyrfx/order/arg_parser_order.py
pyrfx/order/base_deposit.py
pyrfx/order/base_order.py
pyrfx/order/base_withdraw.py
pyrfx/order/decrease.py
pyrfx/order/deposit.py
pyrfx/order/increase.py
pyrfx/order/limit_cancel.py
pyrfx/order/limit_increase.py
pyrfx/order/limit_ioc.py
pyrfx/order/swap.py
pyrfx/order/swap_router.py
pyrfx/order/withdraw.py
pyrfx/utils.py
pyrfx-0.1.14.dist-info/LICENSE
pyrfx-0.1.14.dist-info/METADATA
pyrfx-0.1.14.dist-info/WHEEL
pyrfx-0.1.14.dist-info/RECORD
