Metadata-Version: 2.3
Name: pyrfx
Version: 0.1.14
Summary: A comprehensive Python SDK for interacting with RFX contracts and data.
License: MIT
Keywords: SDK,RFX,blockchain,Python,DeFi,DEX,Exchange
Author: RFX Dev
Author-email: dev@rfx.exchange
Maintainer: RFX Dev
Maintainer-email: dev@rfx.exchange
Requires-Python: >=3.10,<4
Classifier: License :: OSI Approved :: MIT License
Classifier: Operating System :: OS Independent
Classifier: Programming Language :: Python :: 3
Classifier: Programming Language :: Python :: 3.10
Classifier: Programming Language :: Python :: 3.11
Classifier: Programming Language :: Python :: 3.12
Classifier: Programming Language :: Python :: 3.13
Requires-Dist: eth-abi (>=5.1.0,<6.0.0)
Requires-Dist: hexbytes (>=1.2.1,<2.0.0)
Requires-Dist: numpy (>=2.1.2,<3.0.0)
Requires-Dist: pandas (>=2.2.3,<3.0.0)
Requires-Dist: ratelimit (>=2.2.1,<3.0.0)
Requires-Dist: tenacity (>=9.0.0,<10.0.0)
Requires-Dist: web3 (>=7.3.0,<8.0.0)
Project-URL: Documentation, https://rfx.exchange
Project-URL: Homepage, https://rfx.exchange
Project-URL: Repository, https://github.com/relative-finance/pyrfx
